{ "id": "spicy-frontier", "name": "Spicy Frontier", "image": "images/spicy-frontier.webp", "description": "A bold, spicy take on the Red Frontier with chili-infused rum and warm spices. A fiery cocktail for the adventurous.", "keywords": ["spicy", "chili cocktail", "rum", "red frontier", "bold"], "flavorProfile": "Hot, rich and spiced with warmth from chili and cinnamon, balanced by fruity cranberry.", "strength": 7, "ingredients": [ "5 cl Chili-Infused Dark Rum", "5 cl Cranberry Juice", "1 cl Cinnamon Syrup", "1 cl Fresh Lime Juice", "Crushed Ice", "Red Chili Slice (garnish)" ], "instructions": [ "Shake all ingredients with ice.", "Strain over crushed ice into a tumbler.", "Garnish with a red chili slice." ], "externalLinks": {}, "tags": ["spicy", "chili", "rum", "warm", "redfrontier"], "variationOf": "red-frontier" }
